libjson/__init__.py
libjson/json_helper.py
libmail/__init__.py
libmail/mail_style_text_convertor.py
libmail/smtp_mail_sender.py
libmongodb/__init__.py
libmongodb/mongo_client_helper.py
libsnmp/__init__.py
libsnmp/snmp_define.py
libsnmp/snmp_get_interface.py
libsnmp/snmp_send_interface.py
libsnmp/snmp_trap_interface.py
libsql/__init__.py
libsql/sqlite_client.py
libutil/__init__.py
libutil/file_io_helper.py
libutil/logger.py
libutil/path_test.py
libutil/string_buffer_bulk_writer.py
libutil/system_baloon_tip.py
libutil/tts_module.py
libutil/window_toast_notify.py
libutil/windows_modules.py
zks_pylib-1.0.2.dist-info/LICENSE
zks_pylib-1.0.2.dist-info/METADATA
zks_pylib-1.0.2.dist-info/WHEEL
zks_pylib-1.0.2.dist-info/top_level.txt
zks_pylib-1.0.2.dist-info/RECORD
