Metadata-Version: 2.1
Name: zks-pylib
Version: 1.0.2
Summary: zks pylib
Home-page: https://github.com/pypa/sampleproject
Author: khan
Author-email: acf21s@gmail.com
License: UNKNOWN
Project-URL: Bug Tracker, https://github.com/pypa/sampleproject/issues
Platform: UNKNOWN
Classifier: Programming Language :: Python :: 3
Classifier: License :: OSI Approved :: MIT License
Classifier: Operating System :: OS Independent
